ultrasync_index-0.1.0.dist-info/METADATA
ultrasync_index-0.1.0.dist-info/WHEEL
ultrasync_index/__init__.py
ultrasync_index/ultrasync_index.cpython-314-darwin.so
ultrasync_index-0.1.0.dist-info/RECORD
