Metadata-Version: 2.4
Name: ultrasync-index
Version: 0.1.0
Classifier: Development Status :: 3 - Alpha
Classifier: Intended Audience :: Developers
Classifier: License :: OSI Approved :: MIT License
Classifier: Programming Language :: Python :: 3
Classifier: Programming Language :: Python :: 3.10
Classifier: Programming Language :: Python :: 3.11
Classifier: Programming Language :: Python :: 3.12
Classifier: Programming Language :: Python :: 3.13
Classifier: Programming Language :: Python :: 3.14
Classifier: Programming Language :: Rust
Summary: Rust-backed mmapped index and vector search for ultrasync
Keywords: embeddings,index,mmap,vector-search
Author-email: David Gidwani <david.gidwani@gmail.com>
License: MIT
Requires-Python: >=3.10
Project-URL: Homepage, https://github.com/davidgidwani/ultrasync
Project-URL: Repository, https://github.com/davidgidwani/ultrasync
